hopy/__init__.py
hopy/const.py
hopy/evaluator.py
hopy/lexer.py
hopy/parser.py
hopy-0.0.2.dist-info/LICENSE
hopy-0.0.2.dist-info/METADATA
hopy-0.0.2.dist-info/WHEEL
hopy-0.0.2.dist-info/top_level.txt
hopy-0.0.2.dist-info/RECORD
