Metadata-Version: 2.1
Name: hopy
Version: 0.0.2
Summary: A high level language for predicate evaluation on JSON using JsonPath expressions
Home-page: https://github.com/arpitsingla96/hopy
Author: Arpit Singla
Author-email: arpitsingla96@gmail.com
License: UNKNOWN
Platform: UNKNOWN
Classifier: Programming Language :: Python :: 3.7
Classifier: License :: OSI Approved :: Apache Software License
Classifier: Operating System :: OS Independent
Requires-Python: >=3.7
Provides-Extra: jsonpath_ng
Requires-Dist: jsonpath-ng (>=1.5.0) ; extra == 'jsonpath_ng'
